{
    "张家界": {
        "6日（今天）": {
            "天气": "多云",
            "温度": "36/26℃",
            "风象": "<3级"
        },
        "7日（明天）": {
            "天气": "多云",
            "温度": "37/26℃",
            "风象": "<3级"
        },
        "8日（后天）": {
            "天气": "小雨",
            "温度": "34/25℃",
            "风象": "<3级"
        },
        "9日（周一）": {
            "天气": "小雨转大雨",
            "温度": "31/26℃",
            "风象": "<3级"
        },
        "10日（周二）": {
            "天气": "中雨转小雨",
            "温度": "31/25℃",
            "风象": "<3级"
        },
        "11日（周三）": {
            "天气": "中雨转大雨",
            "温度": "27/23℃",
            "风象": "<3级"
        },
        "12日（周四）": {
            "天气": "小雨转大雨",
            "温度": "25/23℃",
            "风象": "<3级"
        }
    }
}